contextual_chunker/__init__.py
contextual_chunker/chunker.py
contextual_chunker/cli.py
contextual_chunker-0.1.0.dist-info/licenses/LICENSE
contextual_chunker-0.1.0.dist-info/METADATA
contextual_chunker-0.1.0.dist-info/WHEEL
contextual_chunker-0.1.0.dist-info/entry_points.txt
contextual_chunker-0.1.0.dist-info/top_level.txt
contextual_chunker-0.1.0.dist-info/RECORD
