Metadata-Version: 2.4
Name: contextual-chunker
Version: 0.1.0
Summary: A comprehensive document chunking library with context generation for RAG applications
Home-page: https://github.com/KISHAN8888/contextual-chunker
Author: Kishan Tripathi
Author-email: Kishan Tripathi <kishantripathi888@gmail.com>
License: MIT
Project-URL: Homepage, https://github.com/KISHAN8888/contextual-chunker
Project-URL: Repository, https://github.com/KISHAN8888/contextual-chunker.git
Project-URL: Issues, https://github.com/KISHAN8888/contextual-chunker/issues
Classifier: Development Status :: 3 - Alpha
Classifier: Intended Audience :: Developers
Classifier: License :: OSI Approved :: MIT License
Classifier: Operating System :: OS Independent
Classifier: Programming Language :: Python :: 3
Classifier: Programming Language :: Python :: 3.8
Classifier: Programming Language :: Python :: 3.9
Classifier: Programming Language :: Python :: 3.10
Classifier: Programming Language :: Python :: 3.11
Classifier: Topic :: Software Development :: Libraries :: Python Modules
Classifier: Topic :: Text Processing
Classifier: Topic :: Scientific/Engineering :: Artificial Intelligence
Requires-Python: >=3.8
License-File: LICENSE
Requires-Dist: openai>=1.0.0
Requires-Dist: tqdm>=4.64.0
Requires-Dist: python-dotenv>=0.19.0
Requires-Dist: PyPDF2>=3.0.0
Requires-Dist: PyMuPDF>=1.20.0
Provides-Extra: dev
Requires-Dist: pytest>=7.0.0; extra == "dev"
Requires-Dist: black>=22.0.0; extra == "dev"
Requires-Dist: flake8>=4.0.0; extra == "dev"
Dynamic: author
Dynamic: home-page
Dynamic: license-file
Dynamic: requires-python
